django_backend_utils/__init__.py
django_backend_utils/admin.py
django_backend_utils/apps.py
django_backend_utils/context_processors.py
django_backend_utils/dynamic.py
django_backend_utils/firebase_init.py
django_backend_utils/models.py
django_backend_utils/responses.py
django_backend_utils/serializer.py
django_backend_utils/urls.py
django_backend_utils/utils.py
django_backend_utils/views.py
django_backend_utils-0.0.1.dist-info/licenses/LICENSE
django_backend_utils-0.0.1.dist-info/METADATA
django_backend_utils-0.0.1.dist-info/WHEEL
django_backend_utils-0.0.1.dist-info/top_level.txt
django_backend_utils-0.0.1.dist-info/RECORD
