Metadata-Version: 2.4
Name: django_backend_utils
Version: 0.0.1
Summary: A django Backend Utils For Laxnit Tech projects
Home-page: https://link.com
Author: Dennis Kamau
Author-email: kamadennis05@gmail.com
Classifier: Framework :: Django
Classifier: Programming Language :: Python :: 3
Classifier: License :: OSI Approved :: MIT License
Classifier: Operating System :: OS Independent
Requires-Python: >=3.10
License-File: LICENSE
Requires-Dist: Django>=4.1.2
Dynamic: author
Dynamic: author-email
Dynamic: classifier
Dynamic: description
Dynamic: description-content-type
Dynamic: home-page
Dynamic: license-file
Dynamic: requires-dist
Dynamic: requires-python
Dynamic: summary
